md_to_pdf/md_to_pdf.py
md_to_pdf-0.1.0.dist-info/LICENSE
md_to_pdf-0.1.0.dist-info/WHEEL
md_to_pdf-0.1.0.dist-info/METADATA
md_to_pdf-0.1.0.dist-info/RECORD
