Metadata-Version: 2.1
Name: md-to-pdf
Version: 0.1.0
Summary: Yet another Markdown to PDF converter
Home-page: https://github.com/vpoulailleau/md-to-pdf
License: BSD-3-Clause
Keywords: Markdown,PDF,PDF generation,PDF converter,converter
Author: Vincent Poulailleau
Author-email: vpoulailleau@gmail.com
Requires-Python: >=3.7,<4.0
Classifier: License :: OSI Approved :: BSD License
Classifier: Operating System :: OS Independent
Classifier: Programming Language :: Python :: 3
Classifier: Programming Language :: Python :: 3.7
Classifier: Programming Language :: Python :: 3.8
Classifier: Programming Language :: Python :: 3.9
Project-URL: Documentation, https://github.com/vpoulailleau/md-to-pdf
Project-URL: Repository, https://github.com/vpoulailleau/md-to-pdf
